GCNCharge/GCNCharge.py
GCNCharge/__init__.py
GCNCharge/atom_init.json
GCNCharge/cof.pkl
GCNCharge/cof.pth
GCNCharge/mof.pkl
GCNCharge/mof.pth
test/Cu-BTC.cif
test/__init__.py
GCNCharge-1.1.1.dist-info/LICENSE
GCNCharge-1.1.1.dist-info/METADATA
GCNCharge-1.1.1.dist-info/WHEEL
GCNCharge-1.1.1.dist-info/top_level.txt
GCNCharge-1.1.1.dist-info/RECORD
