Metadata-Version: 2.1
Name: GCNCharge
Version: 1.1.1
Summary: A partial atomic charge of nanoporous materials predicter
Home-page: https://github.com/sxm13/GCNCharges
Author: Guobin Zhao
Author-email: sxmzhaogb@gmai.com
License: MIT
Classifier: Programming Language :: Python :: 3
Classifier: License :: OSI Approved :: MIT License
License-File: LICENSE
Requires-Dist: numpy >=1.13.3
Requires-Dist: pymatgen >=2018.6.11
Requires-Dist: ase >=3.19
Requires-Dist: tqdm >=4.15
Requires-Dist: pandas >=0.20.3
Requires-Dist: scikit-learn >=0.19.1
Requires-Dist: joblib >=0.13.2
Requires-Dist: torch
